kahi_impactu_utils/String.py
kahi_impactu_utils/Utils.py
kahi_impactu_utils/__init__.py
kahi_impactu_utils/_version.py
Kahi_impactu_utils-0.1.5.dist-info/LICENSE
Kahi_impactu_utils-0.1.5.dist-info/METADATA
Kahi_impactu_utils-0.1.5.dist-info/WHEEL
Kahi_impactu_utils-0.1.5.dist-info/top_level.txt
Kahi_impactu_utils-0.1.5.dist-info/RECORD
