Metadata-Version: 2.1
Name: Kahi_impactu_utils
Version: 0.1.5
Summary: Utils for Kahi Impactu project.
Home-page: https://github.com/colav/Kahi_impactu_utils
Author: Colav
Author-email: colav@udea.edu.co
License: BSD
License-File: LICENSE
Requires-Dist: langid~=1.1.6
Requires-Dist: lingua-language-detector~=1.3.3
Requires-Dist: pycld2~=0.41
Requires-Dist: langdetect~=1.0.7
Requires-Dist: fastspell~=0.8.0
Requires-Dist: iso639~=0.1.4
Requires-Dist: unidecode
Requires-Dist: titlecase
